odoo8_addon_sale_quotation_sourcing-8.0.0.3.1.99.dev39-py3.8-nspkg.pth
odoo_addons/sale_quotation_sourcing/README.rst
odoo_addons/sale_quotation_sourcing/__init__.py
odoo_addons/sale_quotation_sourcing/__openerp__.py
odoo_addons/sale_quotation_sourcing/data/exceptions.xml
odoo_addons/sale_quotation_sourcing/i18n/am.po
odoo_addons/sale_quotation_sourcing/i18n/ar.po
odoo_addons/sale_quotation_sourcing/i18n/bg.po
odoo_addons/sale_quotation_sourcing/i18n/bs.po
odoo_addons/sale_quotation_sourcing/i18n/ca.po
odoo_addons/sale_quotation_sourcing/i18n/ca_ES.po
odoo_addons/sale_quotation_sourcing/i18n/cs.po
odoo_addons/sale_quotation_sourcing/i18n/da.po
odoo_addons/sale_quotation_sourcing/i18n/de.po
odoo_addons/sale_quotation_sourcing/i18n/el_GR.po
odoo_addons/sale_quotation_sourcing/i18n/en_AU.po
odoo_addons/sale_quotation_sourcing/i18n/en_GB.po
odoo_addons/sale_quotation_sourcing/i18n/es.po
odoo_addons/sale_quotation_sourcing/i18n/es_AR.po
odoo_addons/sale_quotation_sourcing/i18n/es_CL.po
odoo_addons/sale_quotation_sourcing/i18n/es_CO.po
odoo_addons/sale_quotation_sourcing/i18n/es_CR.po
odoo_addons/sale_quotation_sourcing/i18n/es_DO.po
odoo_addons/sale_quotation_sourcing/i18n/es_EC.po
odoo_addons/sale_quotation_sourcing/i18n/es_ES.po
odoo_addons/sale_quotation_sourcing/i18n/es_MX.po
odoo_addons/sale_quotation_sourcing/i18n/es_PE.po
odoo_addons/sale_quotation_sourcing/i18n/es_PY.po
odoo_addons/sale_quotation_sourcing/i18n/es_VE.po
odoo_addons/sale_quotation_sourcing/i18n/et.po
odoo_addons/sale_quotation_sourcing/i18n/fa.po
odoo_addons/sale_quotation_sourcing/i18n/fi.po
odoo_addons/sale_quotation_sourcing/i18n/fr.po
odoo_addons/sale_quotation_sourcing/i18n/fr_CA.po
odoo_addons/sale_quotation_sourcing/i18n/fr_CH.po
odoo_addons/sale_quotation_sourcing/i18n/fr_FR.po
odoo_addons/sale_quotation_sourcing/i18n/gl.po
odoo_addons/sale_quotation_sourcing/i18n/gl_ES.po
odoo_addons/sale_quotation_sourcing/i18n/he.po
odoo_addons/sale_quotation_sourcing/i18n/hi.po
odoo8_addon_sale_quotation_sourcing-8.0.0.3.1.99.dev39.dist-info/METADATA
odoo8_addon_sale_quotation_sourcing-8.0.0.3.1.99.dev39.dist-info/WHEEL
odoo8_addon_sale_quotation_sourcing-8.0.0.3.1.99.dev39.dist-info/namespace_packages.txt
odoo8_addon_sale_quotation_sourcing-8.0.0.3.1.99.dev39.dist-info/top_level.txt
odoo8_addon_sale_quotation_sourcing-8.0.0.3.1.99.dev39.dist-info/RECORD
