Metadata-Version: 2.1
Name: odoo8-addon-sale-quotation-sourcing
Version: 8.0.0.3.1.99.dev39
Summary: manual sourcing of sale quotations
Home-page: http://www.camptocamp.com
Author: Camptocamp,Odoo Community Association (OCA)
Author-email: support@odoo-community.org
License: UNKNOWN
Platform: UNKNOWN
Classifier: Programming Language :: Python
Classifier: Framework :: Odoo
Classifier: Framework :: Odoo :: 8.0
Requires-Python: ~=2.7
Requires-Dist: odoo8-addon-sale-exceptions
Requires-Dist: odoo8-addon-sale-procurement-group-by-line
Requires-Dist: odoo (<9.0a,>=8.0a)
